{
    "name": "Rogerforner\\ScoolProgramming\\Models\\ProfessionalModule",
    "line": 9,
    "short_desc": "",
    "long_desc": "",
    "hint": null,
    "tags": [],
    "namespace": "Rogerforner\\ScoolProgramming\\Models",
    "file": "D:\\www\\programming\\packages\\rogerforner\\scool_programming\/\\src\\Models\\ProfessionalModule.php",
    "relative_file": null,
    "hash": "9d8711441f4d3cc3eff2185a8cc43c2d5b2a8ce4",
    "parent": "Illuminate\\Database\\Eloquent\\Model",
    "modifiers": 0,
    "is_trait": false,
    "is_interface": false,
    "aliases": {
        "Model": "Illuminate\\Database\\Eloquent\\Model",
        "Department": "Rogerforner\\ScoolProgramming\\Models\\Department",
        "TrainingUnit": "Rogerforner\\ScoolProgramming\\Models\\TrainingUnit"
    },
    "errors": [],
    "interfaces": [],
    "traits": [],
    "properties": {
        "fillable": {
            "name": "fillable",
            "line": 19,
            "short_desc": "The attributes that are mass assignable.",
            "long_desc": "",
            "hint": [
                [
                    "array",
                    false
                ]
            ],
            "hint_desc": "",
            "tags": [],
            "modifiers": 2,
            "default": {
                "nodeType": "Expr_Array",
                "items": [
                    {
                        "nodeType": "Expr_ArrayItem",
                        "key": null,
                        "value": {
                            "nodeType": "Scalar_String",
                            "value": "mp",
                            "attributes": {
                                "startLine": 20,
                                "endLine": 20,
                                "kind": 1
                            }
                        },
                        "byRef": false,
                        "attributes": {
                            "startLine": 20,
                            "endLine": 20
                        }
                    },
                    {
                        "nodeType": "Expr_ArrayItem",
                        "key": null,
                        "value": {
                            "nodeType": "Scalar_String",
                            "value": "name",
                            "attributes": {
                                "startLine": 21,
                                "endLine": 21,
                                "kind": 1
                            }
                        },
                        "byRef": false,
                        "attributes": {
                            "startLine": 21,
                            "endLine": 21
                        }
                    },
                    {
                        "nodeType": "Expr_ArrayItem",
                        "key": null,
                        "value": {
                            "nodeType": "Scalar_String",
                            "value": "section1",
                            "attributes": {
                                "startLine": 22,
                                "endLine": 22,
                                "kind": 1
                            }
                        },
                        "byRef": false,
                        "attributes": {
                            "startLine": 22,
                            "endLine": 22
                        }
                    },
                    {
                        "nodeType": "Expr_ArrayItem",
                        "key": null,
                        "value": {
                            "nodeType": "Scalar_String",
                            "value": "section2",
                            "attributes": {
                                "startLine": 23,
                                "endLine": 23,
                                "kind": 1
                            }
                        },
                        "byRef": false,
                        "attributes": {
                            "startLine": 23,
                            "endLine": 23
                        }
                    },
                    {
                        "nodeType": "Expr_ArrayItem",
                        "key": null,
                        "value": {
                            "nodeType": "Scalar_String",
                            "value": "section3",
                            "attributes": {
                                "startLine": 24,
                                "endLine": 24,
                                "kind": 1
                            }
                        },
                        "byRef": false,
                        "attributes": {
                            "startLine": 24,
                            "endLine": 24
                        }
                    },
                    {
                        "nodeType": "Expr_ArrayItem",
                        "key": null,
                        "value": {
                            "nodeType": "Scalar_String",
                            "value": "section4",
                            "attributes": {
                                "startLine": 25,
                                "endLine": 25,
                                "kind": 1
                            }
                        },
                        "byRef": false,
                        "attributes": {
                            "startLine": 25,
                            "endLine": 25
                        }
                    },
                    {
                        "nodeType": "Expr_ArrayItem",
                        "key": null,
                        "value": {
                            "nodeType": "Scalar_String",
                            "value": "approved",
                            "attributes": {
                                "startLine": 26,
                                "endLine": 26,
                                "kind": 1
                            }
                        },
                        "byRef": false,
                        "attributes": {
                            "startLine": 26,
                            "endLine": 26
                        }
                    },
                    {
                        "nodeType": "Expr_ArrayItem",
                        "key": null,
                        "value": {
                            "nodeType": "Scalar_String",
                            "value": "public",
                            "attributes": {
                                "startLine": 27,
                                "endLine": 27,
                                "kind": 1
                            }
                        },
                        "byRef": false,
                        "attributes": {
                            "startLine": 27,
                            "endLine": 27
                        }
                    },
                    {
                        "nodeType": "Expr_ArrayItem",
                        "key": null,
                        "value": {
                            "nodeType": "Scalar_String",
                            "value": "department_id",
                            "attributes": {
                                "startLine": 28,
                                "endLine": 28,
                                "kind": 1
                            }
                        },
                        "byRef": false,
                        "attributes": {
                            "startLine": 28,
                            "endLine": 28
                        }
                    },
                    {
                        "nodeType": "Expr_ArrayItem",
                        "key": null,
                        "value": {
                            "nodeType": "Scalar_String",
                            "value": "created_by",
                            "attributes": {
                                "startLine": 29,
                                "endLine": 29,
                                "kind": 1
                            }
                        },
                        "byRef": false,
                        "attributes": {
                            "startLine": 29,
                            "endLine": 29
                        }
                    },
                    {
                        "nodeType": "Expr_ArrayItem",
                        "key": null,
                        "value": {
                            "nodeType": "Scalar_String",
                            "value": "updated_by",
                            "attributes": {
                                "startLine": 30,
                                "endLine": 30,
                                "kind": 1
                            }
                        },
                        "byRef": false,
                        "attributes": {
                            "startLine": 30,
                            "endLine": 30
                        }
                    }
                ],
                "attributes": {
                    "startLine": 19,
                    "endLine": 31,
                    "kind": 2
                }
            },
            "errors": []
        }
    },
    "methods": {
        "department": {
            "name": "department",
            "line": 40,
            "short_desc": "Department.",
            "long_desc": "Get the department of the professional module.",
            "hint": null,
            "hint_desc": null,
            "tags": [],
            "modifiers": 1,
            "is_by_ref": "",
            "exceptions": [],
            "errors": [],
            "parameters": []
        },
        "trainingUnits": {
            "name": "trainingUnits",
            "line": 49,
            "short_desc": "Training Units.",
            "long_desc": "Get the training units for the professional module.",
            "hint": null,
            "hint_desc": null,
            "tags": [],
            "modifiers": 1,
            "is_by_ref": "",
            "exceptions": [],
            "errors": [],
            "parameters": []
        }
    },
    "constants": []
}